{"title":"Grafici","markdown":{"yaml":{"title":"Grafici","author":"","subtitle":"","include-in-header":"assets/header.html","format":{"html":{"theme":"cosmo","code-fold":false,"self-contained":true,"toc":true,"toc-depth":3,"toc-expand":3,"message":false,"css":"assets/custom.css"}},"execute":{"echo":false,"warning":false,"message":false},"editor":"visual"},"headingText":"Istogramma","containsRefs":false,"markdown":"\n\n```{=html}\n<style>\n.flex-container {\n  display: flex;\n  flex-wrap: wrap;\n  gap: 2rem;\n  margin-left: -2rem;\n  margin-right: -2rem;\n}\n\n.flex-item {\n  flex: 1 1 48%;\n  min-width: 300px;\n}\n\n.card {\n  background-color: #f9f9f9;\n  padding: 1rem;\n  border-radius: 12px;\n  box-shadow: 0 2px 6px rgba(0,0,0,0.05);\n}\n</style>\n\n<div class=\"flex-container\">\n  <div class=\"flex-item card\">\n```\n\n\n```{r}\nhist(mtcars$mpg,\n     main = \"Istogramma del Consumo (MPG)\",\n     xlab = \"MPG\",\n     col = \"orange\",\n     border = \"white\")\n```\n\n::: tip\n\n#### 🧭 Come si legge un istogramma? – Guida schematica e utile\n\n#### ✅ 1. **Leggi gli assi**\n- **Asse X (orizzontale)**: rappresenta gli **intervalli dei valori** della variabile (es. consumo, età, punteggi).\n- **Asse Y (verticale)**: mostra la **frequenza** (quante osservazioni cadono in ciascun intervallo).\n\n#### ✅ 2. **Osserva la forma generale**\n- **Simmetrica** → distribuzione equilibrata intorno alla media.\n- **Asimmetrica a destra** → pochi valori molto alti (coda lunga a destra).\n- **Asimmetrica a sinistra** → pochi valori molto bassi.\n- **A campana** → simile a una distribuzione normale.\n- **Multimodale** → più picchi = possibili gruppi o sottocategorie.\n\n#### ✅ 3. **Identifica la modalità**\n- La **barra più alta** mostra l’intervallo **più frequente**.\n- Ti dà un’indicazione della **tendenza centrale**.\n\n#### ✅ 4. **Analizza la dispersione**\n- **Barre distribuite su intervalli ampi** → alta variabilità nei dati.\n- **Barre concentrate in uno stretto intervallo** → bassa variabilità.\n\n#### ✅ 5. **Cerca outlier o code**\n- **Barre isolate** → possibili **valori anomali (outlier)**.\n- **Code lunghe** → valori estremi meno frequenti.\n\n---\n\n### 📌 Riepilogo – Schema utile\n\n| Aspetto                  | Cosa guardare                       | Cosa indica                              |\n|--------------------------|-------------------------------------|-------------------------------------------|\n| **Asse X**               | Intervalli della variabile          | Cosa stai misurando                       |\n| **Asse Y**               | Altezza delle barre                 | Frequenza delle osservazioni              |\n| **Barra più alta**       | Valore/modo più frequente           | Tendenza centrale                         |\n| **Forma simmetrica o no**| Asimmetria o code                   | Squilibri, outlier                        |\n| **Larghezza complessiva**| Base dell’istogramma                | Variazione/dispersione nei dati           |\n\n:::\n\n\n## Boxplot\n```{=html}\n<style>\n.flex-container {\n  display: flex;\n  flex-wrap: wrap;\n  gap: 2rem;\n  margin-left: -2rem;\n  margin-right: -2rem;\n}\n\n.flex-item {\n  flex: 1 1 48%;\n  min-width: 300px;\n}\n\n.card {\n  background-color: #f9f9f9;\n  padding: 1rem;\n  border-radius: 12px;\n  box-shadow: 0 2px 6px rgba(0,0,0,0.05);\n}\n</style>\n\n<div class=\"flex-container\">\n  <div class=\"flex-item card\">\n```\n\n```{r}\nboxplot(mpg ~ as.factor(cyl), data = mtcars,\n        main = \"Boxplot MPG per Cilindri\",\n        xlab = \"Numero di cilindri\",\n        ylab = \"MPG\",\n        col = \"lightblue\")\n```\n\n::: tip\n\n#### 📦 Come si legge un boxplot? – Guida schematica e utile\n\n#### ✅ 1. **Comprendi gli elementi base**\n- **Linea centrale nella scatola**: è la **mediana** (valore centrale).\n- **Bordi della scatola (box)**: indicano il **1° quartile (Q1)** e il **3° quartile (Q3)** → contengono il 50% centrale dei dati.\n- **\"Whiskers\" (linee esterne)**: si estendono fino ai dati **non considerati outlier**, solitamente entro 1.5 × IQR.\n- **Punti isolati fuori dai whiskers**: sono **outlier** (valori anomali).\n\n#### ✅ 2. **Valuta la simmetria**\n- Se la mediana è **centrata nella scatola** e i whisker sono di lunghezza simile → distribuzione **simmetrica**.\n- Se la mediana è **spostata** o un whisker è molto più lungo → **asimmetria**.\n\n#### ✅ 3. **Analizza la dispersione**\n- **Larghezza della scatola (Q3 - Q1)** = **Intervallo Interquartile (IQR)** → misura la **variabilità centrale** dei dati.\n- **Whisker lunghi** → valori più dispersi.\n- **Whisker corti** → valori più concentrati.\n\n#### ✅ 4. **Individua gli outlier**\n- Punti fuori dai whiskers → **valori estremi**.\n- Importante valutarli nel contesto: errori? valori reali ma rari?\n\n---\n\n### 📌 Riepilogo – Schema utile\n\n| Elemento         | Cosa rappresenta                        | Cosa ci dice                             |\n|------------------|------------------------------------------|-------------------------------------------|\n| **Linea centrale** | Mediana                                 | Tendenza centrale                         |\n| **Box (Q1 - Q3)** | Intervallo interquartile (IQR)           | Variabilità centrale                      |\n| **Whiskers**      | Dati non-outlier                         | Dispersione esterna                       |\n| **Outlier**       | Valori fuori da 1.5 × IQR                | Valori estremi (da approfondire)          |\n| **Simmetria**     | Posizione mediana e lunghezza whiskers   | Forma della distribuzione (asimmetrie)    |\n\n:::\n\n\n## Violin Plot\n```{=html}\n<style>\n.flex-container {\n  display: flex;\n  flex-wrap: wrap;\n  gap: 2rem;\n  margin-left: -2rem;\n  margin-right: -2rem;\n}\n\n.flex-item {\n  flex: 1 1 48%;\n  min-width: 300px;\n}\n\n.card {\n  background-color: #f9f9f9;\n  padding: 1rem;\n  border-radius: 12px;\n  box-shadow: 0 2px 6px rgba(0,0,0,0.05);\n}\n</style>\n\n<div class=\"flex-container\">\n  <div class=\"flex-item card\">\n```\n\n```{r}\nlibrary(ggplot2)\nggplot(mtcars, aes(x = factor(cyl), y = mpg)) +\n  geom_violin(fill = \"lightblue\") +\n  geom_boxplot(width = 0.1) +\n  labs(title = \"Violin Plot: MPG per Cilindri\",\n       x = \"Cilindri\", y = \"MPG\")\n```\n::: tip\n\n#### 🎻 Come si legge un violin plot? – Guida schematica e utile\n\n#### ✅ 1. **Interpreta le componenti**\n- **Forma a “violino”**: rappresenta la **distribuzione dei dati** tramite una curva di densità speculare.\n- **Larghezza** in ciascun punto verticale: indica **quanto sono frequenti i valori** in quell’intervallo.\n- **Linea interna o box centrale** (opzionale): include **mediana** e **intervallo interquartile (IQR)**, come in un boxplot.\n\n#### ✅ 2. **Valuta la densità**\n- Le **zone più larghe** rappresentano **concentrazioni di dati**.\n- Le **zone più strette** indicano valori meno frequenti.\n- A differenza del boxplot, la distribuzione non è limitata a una forma rettangolare → puoi vedere la **forma reale della distribuzione**.\n\n#### ✅ 3. **Analizza la simmetria**\n- Se le due metà del violino sono **simmetriche** → distribuzione bilanciata.\n- Se una metà è più larga o più lunga → **asimmetria**.\n\n#### ✅ 4. **Combina con il boxplot interno**\n- Se presente, il **box centrale** fornisce la **mediana** e il **range interquartile**.\n- Aiuta a confrontare **forma e centro della distribuzione** contemporaneamente.\n\n---\n\n### 📌 Riepilogo – Schema utile\n\n| Elemento               | Cosa rappresenta                        | Cosa ci dice                              |\n|------------------------|------------------------------------------|--------------------------------------------|\n| **Larghezza del violino** | Densità di dati in ogni intervallo     | Frequenza relativa                         |\n| **Forma complessiva**     | Distribuzione                         | Simmetria, multimodalità                   |\n| **Box centrale (se presente)** | Mediana + IQR                   | Tendenza centrale e variabilità            |\n| **Estremità del violino**  | Code della distribuzione              | Valori estremi (non necessariamente outlier) |\n| **Asimmetria visiva**     | Differenza tra le due metà            | Squilibri nei dati                         |\n\n:::\n\n\n## QQ plot\n```{=html}\n<style>\n.flex-container {\n  display: flex;\n  flex-wrap: wrap;\n  gap: 2rem;\n  margin-left: -2rem;\n  margin-right: -2rem;\n}\n\n.flex-item {\n  flex: 1 1 48%;\n  min-width: 300px;\n}\n\n.card {\n  background-color: #f9f9f9;\n  padding: 1rem;\n  border-radius: 12px;\n  box-shadow: 0 2px 6px rgba(0,0,0,0.05);\n}\n</style>\n\n<div class=\"flex-container\">\n  <div class=\"flex-item card\">\n```\n\n\n```{r}\nqqnorm(mtcars$mpg,\n       main = \"QQ-Plot per MPG\")\nqqline(mtcars$mpg, col = \"red\")\n```\n\n::: tip\n\n#### 📈 Come si legge un Q-Q plot? – Guida schematica e utile\n\n#### ✅ 1. **Cos’è un Q-Q plot?**\n- Un **Q-Q plot** confronta i **quantili di una variabile osservata** con i **quantili di una distribuzione teorica** (di solito **normale**).\n- Serve per **verificare se i dati seguono una certa distribuzione**.\n\n#### ✅ 2. **Leggi l’asse X e Y**\n- **Asse X**: quantili attesi (dalla distribuzione teorica).\n- **Asse Y**: quantili osservati (dai tuoi dati).\n\n---\n\n#### ✅ 3. **Interpreta l’allineamento**\n- Se i punti stanno **sulla linea diagonale** (linea di riferimento) → i dati **seguono la distribuzione teorica** (es. distribuzione normale).\n- Se i punti **deviano dalla linea** → i dati **non seguono la distribuzione attesa**.\n\n---\n\n#### ✅ 4. **Analizza le deviazioni**\n- **Deviazione in alto o in basso alle estremità** → i dati hanno **code più pesanti o leggere** rispetto alla distribuzione teorica.\n- **Curvatura a S o a gomito** → indica **asimmetria** o **skewness**:\n  - Curva **a S (convessa-concava)** → coda lunga a destra (**asimmetria positiva**).\n  - Curva **a gomito (concava-convessa)** → coda lunga a sinistra (**asimmetria negativa**).\n\n---\n\n### 📌 Riepilogo – Schema utile\n\n| Aspetto                      | Cosa osservare                          | Cosa indica                             |\n|------------------------------|------------------------------------------|------------------------------------------|\n| **Allineamento dei punti**   | Segue la linea diagonale                | I dati seguono la distribuzione teorica  |\n| **Deviazione alle estremità**| Code più o meno pesanti                 | Differenze nella coda                    |\n| **Curvatura dei punti**      | Forma a S o a gomito                    | Asimmetria (skewness)                    |\n| **Distribuzione di confronto** | Di solito normale (ma può variare)   | Deve essere nota per interpretare correttamente |\n\n:::\n\n## Scatter-plot\n```{=html}\n<style>\n.flex-container {\n  display: flex;\n  flex-wrap: wrap;\n  gap: 2rem;\n  margin-left: -2rem;\n  margin-right: -2rem;\n}\n\n.flex-item {\n  flex: 1 1 48%;\n  min-width: 300px;\n}\n\n.card {\n  background-color: #f9f9f9;\n  padding: 1rem;\n  border-radius: 12px;\n  box-shadow: 0 2px 6px rgba(0,0,0,0.05);\n}\n</style>\n\n<div class=\"flex-container\">\n  <div class=\"flex-item card\">\n```\n\n```{r}\nplot(mtcars$hp, mtcars$mpg,\n     main = \"Scatterplot: MPG vs HP\",\n     xlab = \"Cavalli (HP)\",\n     ylab = \"Consumo (MPG)\",\n     pch = 19,\n     col = \"darkgreen\")\n```\n\n\n::: tip\n\n#### 🔵 Come si legge uno scatterplot? – Guida schematica e utile\n\n#### ✅ 1. **Cosa mostra uno scatterplot?**\n- Ogni punto rappresenta **una coppia di valori** per due variabili quantitative (X e Y).\n- Serve a visualizzare **relazioni, tendenze e correlazioni** tra due variabili.\n\n---\n\n#### ✅ 2. **Leggi gli assi**\n- **Asse X (orizzontale)**: variabile indipendente (predictor).\n- **Asse Y (verticale)**: variabile dipendente (risposta).\n\n---\n\n#### ✅ 3. **Osserva la tendenza generale**\n- **Andamento crescente (↗)**: **correlazione positiva** → all’aumentare di X, aumenta anche Y.\n- **Andamento decrescente (↘)**: **correlazione negativa** → all’aumentare di X, Y diminuisce.\n- **Nessun andamento visibile**: **assenza di correlazione** → i dati sono sparsi casualmente.\n\n---\n\n#### ✅ 4. **Valuta la forza della relazione**\n- **Punti vicini a una linea ideale** → relazione forte.\n- **Punti molto dispersi** → relazione debole.\n- La forza può essere valutata visivamente o con il coefficiente di correlazione.\n\n---\n\n#### ✅ 5. **Cerca pattern o anomalie**\n- **Gruppi separati** → possibili sottogruppi (cluster).\n- **Andamenti curvi/non lineari** → possibile **relazione non lineare**.\n- **Punti lontani dalla nuvola** → **outlier** (valori anomali).\n\n---\n\n### 📌 Riepilogo – Schema utile\n\n| Aspetto                  | Cosa osservare                      | Cosa indica                              |\n|--------------------------|--------------------------------------|-------------------------------------------|\n| **Distribuzione dei punti** | Densità, forma, direzione          | Tipo di relazione (positiva, negativa, nulla) |\n| **Linearità**             | Allineamento lungo una retta        | Relazione lineare                         |\n| **Dispersione**           | Vicinanza dei punti                 | Forza della correlazione                  |\n| **Outlier**               | Punti isolati                       | Valori anomali da approfondire            |\n| **Pattern insoliti**      | Curve, gruppi, archi                | Relazioni non lineari o sottogruppi       |\n\n:::\n\n## Residual plot\n```{=html}\n<style>\n.flex-container {\n  display: flex;\n  flex-wrap: wrap;\n  gap: 2rem;\n  margin-left: -2rem;\n  margin-right: -2rem;\n}\n\n.flex-item {\n  flex: 1 1 48%;\n  min-width: 300px;\n}\n\n.card {\n  background-color: #f9f9f9;\n  padding: 1rem;\n  border-radius: 12px;\n  box-shadow: 0 2px 6px rgba(0,0,0,0.05);\n}\n</style>\n\n<div class=\"flex-container\">\n  <div class=\"flex-item card\">\n```\n\n```{r}\nmodel <- lm(mpg ~ hp, data = mtcars)\nplot(model$fitted.values, residuals(model),\n     main = \"Residual Plot\",\n     xlab = \"Fitted Values\",\n     ylab = \"Residui\",\n     pch = 19,\n     col = \"purple\")\nabline(h = 0, col = \"red\", lty = 2)\n```\n\n::: tip\n\n#### ♻️ Come si legge un residual plot? – Guida schematica e utile\n\n#### ✅ 1. **Cos’è un residual plot?**\n- Mostra i **residui** (errori) di un modello di regressione → la differenza tra i valori osservati e quelli previsti.\n- Asse X: valori **predetti** dal modello.\n- Asse Y: **residui** (valori osservati − valori predetti).\n\n---\n\n#### ✅ 2. **Obiettivo principale**\n- Verificare se i **presupposti della regressione** sono soddisfatti:\n  - Linearità\n  - Omoscedasticità (varianza costante)\n  - Assenza di pattern sistematici\n\n---\n\n#### ✅ 3. **Cosa cercare**\n\n| Pattern                         | Interpretazione                                          |\n|----------------------------------|-----------------------------------------------------------|\n| **Punti distribuiti a caso**     | ✅ Il modello è adeguato (errori casuali, omoscedastici). |\n| **Forma a U o curva**            | ❌ Mancanza di linearità → forse serve un modello non lineare. |\n| **Funnel (apertura/chiusura)**   | ❌ Eteroschedasticità → la varianza degli errori cambia. |\n| **Punti molto distanti**         | ❗ Outlier nei residui → possibili casi problematici.      |\n\n---\n\n#### ✅ 4. **Cosa idealmente si vuole vedere**\n- Una **nuvola di punti** distribuita **in modo casuale** attorno alla linea orizzontale **y = 0**.\n- Nessun pattern evidente → i residui sono indipendenti e distribuiti normalmente con media zero.\n\n---\n\n### 📌 Riepilogo – Schema utile\n\n| Aspetto                      | Cosa osservare                          | Cosa indica                               |\n|------------------------------|------------------------------------------|--------------------------------------------|\n| **Dispersione casuale**      | Punti sparsi intorno a y = 0            | Buon modello lineare                       |\n| **Pattern curvo o forma a U**| Trend sistematici nei residui           | Relazione non lineare                      |\n| **Funnel (cono aperto/chiuso)** | Varianza non costante                 | Eteroschedasticità                         |\n| **Outlier nei residui**      | Punti molto distanti                    | Osservazioni anomale o influenti           |\n:::\n\n## Boxplot per residui gruppi\n```{=html}\n<style>\n.flex-container {\n  display: flex;\n  flex-wrap: wrap;\n  gap: 2rem;\n  margin-left: -2rem;\n  margin-right: -2rem;\n}\n\n.flex-item {\n  flex: 1 1 48%;\n  min-width: 300px;\n}\n\n.card {\n  background-color: #f9f9f9;\n  padding: 1rem;\n  border-radius: 12px;\n  box-shadow: 0 2px 6px rgba(0,0,0,0.05);\n}\n</style>\n\n<div class=\"flex-container\">\n  <div class=\"flex-item card\">\n```\n\n```{r}\nboxplot(residuals(model) ~ mtcars$cyl,\n        main = \"Boxplot dei Residui per Cilindri\",\n        xlab = \"Cilindri\",\n        ylab = \"Residui\",\n        col = \"lightpink\")\n```\n\n::: tip\n\n#### 📦📊 Come si leggono i boxplot dei residui per gruppi? – Guida schematica e utile\n\n#### ✅ 1. **Cosa mostrano questi boxplot?**\n- Confrontano la **distribuzione dei residui** tra diversi **gruppi** (es. trattamenti, categorie).\n- Ogni box rappresenta **la variabilità degli errori** del modello **all’interno di un gruppo**.\n\n---\n\n#### ✅ 2. **Obiettivo principale**\n- Valutare se il modello **si comporta in modo coerente tra i gruppi**:\n  - Varianza simile? → ok\n  - Mediana dei residui ≈ 0? → ok\n  - Outlier concentrati in certi gruppi? → potenziale problema\n\n---\n\n#### ✅ 3. **Cosa osservare nei boxplot**\n\n| Osservazione                         | Interpretazione                                       |\n|--------------------------------------|--------------------------------------------------------|\n| ✅ **Box simili in tutti i gruppi**   | Residui distribuiti in modo coerente → modello stabile |\n| ✅ **Mediane vicine a 0**             | Il modello **non sovrastima né sottostima** i gruppi   |\n| ❌ **Box molto diversi tra gruppi**   | **Eteroschedasticità** → varianza non costante         |\n| ❌ **Mediane lontane da 0**           | **Sistematici errori di stima** per alcuni gruppi      |\n| ❗ **Molti outlier in un gruppo**     | Dati problematici o mal modellati                      |\n\n---\n\n#### ✅ 4. **Quando è utile usarli?**\n- Dopo aver adattato un modello lineare con **variabili categoriali**.\n- Per controllare **presupposti di omoscedasticità** (es. ANOVA, regressione con fattori).\n- Per rilevare **bias o incoerenze tra gruppi**.\n\n---\n\n### 📌 Riepilogo – Schema utile\n\n| Aspetto                     | Cosa osservare                     | Cosa indica                               |\n|-----------------------------|-------------------------------------|--------------------------------------------|\n| **Varianza dei box**        | Simile tra gruppi                  | Omogeneità delle varianze (buono)          |\n| **Mediana**                 | Vicina a 0 in ogni gruppo          | Nessun bias sistematico                    |\n| **Outlier**                 | Concentrati in pochi gruppi        | Possibili anomalie                         |\n| **Differenze forti nei box**| Modello si adatta diversamente     | Violazione presupposti del modello         |\n\n:::\n\n## Diagnostica dei modelli\n```{=html}\n<style>\n.flex-container {\n  display: flex;\n  flex-wrap: wrap;\n  gap: 2rem;\n  margin-left: -2rem;\n  margin-right: -2rem;\n}\n\n.flex-item {\n  flex: 1 1 48%;\n  min-width: 300px;\n}\n\n.card {\n  background-color: #f9f9f9;\n  padding: 1rem;\n  border-radius: 12px;\n  box-shadow: 0 2px 6px rgba(0,0,0,0.05);\n}\n</style>\n\n<div class=\"flex-container\">\n  <div class=\"flex-item card\">\n```\n\n```{r, fig.width=12, fig.height=10}\nlibrary(performance)\nlibrary(see)\n\nmodel <- lm(mpg ~ hp + wt, data = mtcars)\n\ncheck_model(model)\n```\n::: tip\n\n#### 🧾 Interpretazione dei grafici diagnostici – `check_model()`\n\n#### ✅ 1. **Residuals vs Fitted**\n- **Distribuzione casuale** attorno alla linea orizzontale indica:\n  - Corretta specificazione del modello\n  - Varianza costante (omoschedasticità)\n- **Pattern (curve, funnel)** → possibile violazione di linearità o eteroschedasticità.\n\n---\n\n#### ✅ 2. **Q-Q Plot dei residui**\n- **Punti allineati alla diagonale** → i residui seguono una distribuzione normale.\n- **Deviazioni marcate alle estremità** → possibili problemi di normalità (code pesanti o leggere).\n\n---\n\n#### ✅ 3. **Scale-Location (Spread vs Fitted)**\n- Verifica la **costanza della varianza dei residui**.\n- **Dispersione uniforme** → ok.\n- **Funnel o variazioni di ampiezza** → eteroschedasticità.\n\n---\n\n#### ✅ 4. **Residuals vs Leverage**\n- Identifica **osservazioni influenti**.\n- Punti con **alto leverage e residui grandi** → potrebbero avere **impatto eccessivo** sul modello.\n- Da esaminare singolarmente (possibili outlier o errori).\n\n:::\n\n## Predicted vs Actual\n```{=html}\n<style>\n.flex-container {\n  display: flex;\n  flex-wrap: wrap;\n  gap: 2rem;\n  margin-left: -2rem;\n  margin-right: -2rem;\n}\n\n.flex-item {\n  flex: 1 1 48%;\n  min-width: 300px;\n}\n\n.card {\n  background-color: #f9f9f9;\n  padding: 1rem;\n  border-radius: 12px;\n  box-shadow: 0 2px 6px rgba(0,0,0,0.05);\n}\n</style>\n\n<div class=\"flex-container\">\n  <div class=\"flex-item card\">\n```\n\n```{r}\nplot(mtcars$mpg, model$fitted.values,\n     main = \"Predicted vs Actual\",\n     xlab = \"Valori Osservati (MPG)\",\n     ylab = \"Valori Predetti\",\n     pch = 19,\n     col = \"blue\")\nabline(a = 0, b = 1, col = \"red\", lty = 2)\n```\n\n::: tip\n\n#### 🔮 Interpretazione del grafico Predicted vs Actual\n\n#### ✅ 1. **Cosa mostra questo grafico?**\n- Confronta i **valori previsti dal modello** (asse X) con i **valori osservati reali** (asse Y).\n- Utile per valutare **l’accuratezza del modello**: quanto bene le previsioni replicano i dati osservati?\n\n---\n\n#### ✅ 2. **Interpretazione ideale**\n- I punti **dovrebbero allinearsi lungo la diagonale** (linea y = x).\n- Una buona aderenza alla diagonale indica:\n  - Previsioni accurate\n  - Buona capacità del modello di rappresentare i dati reali\n\n---\n\n#### ✅ 3. **Segnali da osservare**\n\n| Comportamento dei punti          | Cosa indica                              |\n|----------------------------------|-------------------------------------------|\n| ✅ Allineamento lungo la diagonale | Previsioni vicine ai valori reali (ottimo) |\n| ❌ Deviazione sistematica         | Bias del modello (sottostima o sovrastima) |\n| ❌ Dispersione elevata            | Previsioni poco precise                   |\n| ❌ Pattern curvi o gruppi         | Modello mal specificato o relazioni non lineari |\n\n---\n\n#### ✅ 4. **Quando usarlo?**\n- In ogni modello di regressione o predizione (lineare, logistico, machine learning).\n- Per valutare la **qualità globale delle previsioni**.\n\n:::\n\n## Curva di potenza\n\n```{=html}\n<style>\n.flex-container {\n  display: flex;\n  flex-wrap: wrap;\n  gap: 2rem;\n  margin-left: -2rem;\n  margin-right: -2rem;\n}\n\n.flex-item {\n  flex: 1 1 48%;\n  min-width: 300px;\n}\n\n.card {\n  background-color: #f9f9f9;\n  padding: 1rem;\n  border-radius: 12px;\n  box-shadow: 0 2px 6px rgba(0,0,0,0.05);\n}\n</style>\n\n<div class=\"flex-container\">\n  <div class=\"flex-item card\">\n```\n\n\n```{r}\n\n\nlibrary(ggplot2)\n\n# Parametri fissi\nn1 <- 30\nn2 <- 30\nalpha <- 0.05\ndf <- n1 + n2 - 2\ncohens_d <- seq(0, 1.5, length.out = 300)\n\n# Funzione per calcolare la potenza\ncalc_power <- function(d) {\n  ncp <- d * sqrt(n1 * n2 / (n1 + n2))  # parametro non centrale\n  crit <- qt(1 - alpha, df)             # soglia critica (test unilaterale)\n  1 - pt(crit, df, ncp)                 # potenza = 1 - P non rilevata\n}\n\n# Applica la funzione a tutta la sequenza di d\npower_vals <- sapply(cohens_d, calc_power)\n\n# Crea un data frame\ndf_power <- data.frame(\n  d = cohens_d,\n  power = power_vals\n)\n\n# Plot con ggplot2\nggplot(df_power, aes(x = d, y = power)) +\n  geom_line(color = \"blue\", size = 1) +\n  geom_hline(yintercept = 0.8, linetype = \"dotted\", color = \"darkgreen\") +\n  geom_vline(xintercept = 0.5, linetype = \"dashed\", color = \"red\") +\n  labs(\n    title = \"Curva di potenza tipica (t-test a due campioni, unilaterale)\",\n    x = \"Cohen's d (dimensione dell'effetto)\",\n    y = \"Potenza (1 - β)\"\n  ) +\n  theme_minimal()\n```\n\n::: tip\n\n#### ⚡ Interpretazione della Curva di Potenza (Power Curve)\n\n#### ✅ 1. **Cos’è la curva di potenza?**\n- Mostra come **la probabilità di rilevare un effetto reale** (potenza statistica) varia al cambiare della dimensione dell’effetto o del numero di osservazioni.\n- Asse X: **Dimensione dell’effetto** o **dimensione del campione (n)**\n- Asse Y: **Potenza statistica** (P = 1 - β), cioè la probabilità di **rifiutare correttamente H₀**.\n\n---\n\n#### ✅ 2. **Interpretazione dei valori**\n- Una potenza ≥ **0.80** (80%) è **considerata adeguata** → bassa probabilità di errore di tipo II.\n- Valori più bassi indicano **scarsa sensibilità del test** → alto rischio di non rilevare un effetto reale.\n- La curva mostra **quanta potenza si guadagna** aumentando il campione o l’effetto.\n\n---\n\n#### ✅ 3. **Cosa osservare nella curva**\n\n| Forma della curva                 | Interpretazione                                      |\n|----------------------------------|------------------------------------------------------|\n| 📈 Curva crescente e appiattita  | All’aumentare di n, la potenza si stabilizza        |\n| 🎯 Punto in cui P ≈ 0.80         | Soglia ottimale per scegliere la dimensione campione |\n| ❗ Curva piatta a valori bassi   | Effetto troppo piccolo per essere rilevabile         |\n\n---\n\n#### ✅ 4. **Quando usarla?**\n- In fase di **pianificazione dello studio** → per determinare **quanti soggetti servono**.\n- Per verificare se un test ha **potenza sufficiente** a rilevare un effetto atteso.\n\n---\n\n### 📌 Obiettivo finale\n- **Assicurarsi che il test abbia un’alta probabilità di successo**, evitando sprechi di risorse o conclusioni false negative.\n\n:::","srcMarkdownNoYaml":"\n\n## Istogramma\n```{=html}\n<style>\n.flex-container {\n  display: flex;\n  flex-wrap: wrap;\n  gap: 2rem;\n  margin-left: -2rem;\n  margin-right: -2rem;\n}\n\n.flex-item {\n  flex: 1 1 48%;\n  min-width: 300px;\n}\n\n.card {\n  background-color: #f9f9f9;\n  padding: 1rem;\n  border-radius: 12px;\n  box-shadow: 0 2px 6px rgba(0,0,0,0.05);\n}\n</style>\n\n<div class=\"flex-container\">\n  <div class=\"flex-item card\">\n```\n\n\n```{r}\nhist(mtcars$mpg,\n     main = \"Istogramma del Consumo (MPG)\",\n     xlab = \"MPG\",\n     col = \"orange\",\n     border = \"white\")\n```\n\n::: tip\n\n#### 🧭 Come si legge un istogramma? – Guida schematica e utile\n\n#### ✅ 1. **Leggi gli assi**\n- **Asse X (orizzontale)**: rappresenta gli **intervalli dei valori** della variabile (es. consumo, età, punteggi).\n- **Asse Y (verticale)**: mostra la **frequenza** (quante osservazioni cadono in ciascun intervallo).\n\n#### ✅ 2. **Osserva la forma generale**\n- **Simmetrica** → distribuzione equilibrata intorno alla media.\n- **Asimmetrica a destra** → pochi valori molto alti (coda lunga a destra).\n- **Asimmetrica a sinistra** → pochi valori molto bassi.\n- **A campana** → simile a una distribuzione normale.\n- **Multimodale** → più picchi = possibili gruppi o sottocategorie.\n\n#### ✅ 3. **Identifica la modalità**\n- La **barra più alta** mostra l’intervallo **più frequente**.\n- Ti dà un’indicazione della **tendenza centrale**.\n\n#### ✅ 4. **Analizza la dispersione**\n- **Barre distribuite su intervalli ampi** → alta variabilità nei dati.\n- **Barre concentrate in uno stretto intervallo** → bassa variabilità.\n\n#### ✅ 5. **Cerca outlier o code**\n- **Barre isolate** → possibili **valori anomali (outlier)**.\n- **Code lunghe** → valori estremi meno frequenti.\n\n---\n\n### 📌 Riepilogo – Schema utile\n\n| Aspetto                  | Cosa guardare                       | Cosa indica                              |\n|--------------------------|-------------------------------------|-------------------------------------------|\n| **Asse X**               | Intervalli della variabile          | Cosa stai misurando                       |\n| **Asse Y**               | Altezza delle barre                 | Frequenza delle osservazioni              |\n| **Barra più alta**       | Valore/modo più frequente           | Tendenza centrale                         |\n| **Forma simmetrica o no**| Asimmetria o code                   | Squilibri, outlier                        |\n| **Larghezza complessiva**| Base dell’istogramma                | Variazione/dispersione nei dati           |\n\n:::\n\n\n## Boxplot\n```{=html}\n<style>\n.flex-container {\n  display: flex;\n  flex-wrap: wrap;\n  gap: 2rem;\n  margin-left: -2rem;\n  margin-right: -2rem;\n}\n\n.flex-item {\n  flex: 1 1 48%;\n  min-width: 300px;\n}\n\n.card {\n  background-color: #f9f9f9;\n  padding: 1rem;\n  border-radius: 12px;\n  box-shadow: 0 2px 6px rgba(0,0,0,0.05);\n}\n</style>\n\n<div class=\"flex-container\">\n  <div class=\"flex-item card\">\n```\n\n```{r}\nboxplot(mpg ~ as.factor(cyl), data = mtcars,\n        main = \"Boxplot MPG per Cilindri\",\n        xlab = \"Numero di cilindri\",\n        ylab = \"MPG\",\n        col = \"lightblue\")\n```\n\n::: tip\n\n#### 📦 Come si legge un boxplot? – Guida schematica e utile\n\n#### ✅ 1. **Comprendi gli elementi base**\n- **Linea centrale nella scatola**: è la **mediana** (valore centrale).\n- **Bordi della scatola (box)**: indicano il **1° quartile (Q1)** e il **3° quartile (Q3)** → contengono il 50% centrale dei dati.\n- **\"Whiskers\" (linee esterne)**: si estendono fino ai dati **non considerati outlier**, solitamente entro 1.5 × IQR.\n- **Punti isolati fuori dai whiskers**: sono **outlier** (valori anomali).\n\n#### ✅ 2. **Valuta la simmetria**\n- Se la mediana è **centrata nella scatola** e i whisker sono di lunghezza simile → distribuzione **simmetrica**.\n- Se la mediana è **spostata** o un whisker è molto più lungo → **asimmetria**.\n\n#### ✅ 3. **Analizza la dispersione**\n- **Larghezza della scatola (Q3 - Q1)** = **Intervallo Interquartile (IQR)** → misura la **variabilità centrale** dei dati.\n- **Whisker lunghi** → valori più dispersi.\n- **Whisker corti** → valori più concentrati.\n\n#### ✅ 4. **Individua gli outlier**\n- Punti fuori dai whiskers → **valori estremi**.\n- Importante valutarli nel contesto: errori? valori reali ma rari?\n\n---\n\n### 📌 Riepilogo – Schema utile\n\n| Elemento         | Cosa rappresenta                        | Cosa ci dice                             |\n|------------------|------------------------------------------|-------------------------------------------|\n| **Linea centrale** | Mediana                                 | Tendenza centrale                         |\n| **Box (Q1 - Q3)** | Intervallo interquartile (IQR)           | Variabilità centrale                      |\n| **Whiskers**      | Dati non-outlier                         | Dispersione esterna                       |\n| **Outlier**       | Valori fuori da 1.5 × IQR                | Valori estremi (da approfondire)          |\n| **Simmetria**     | Posizione mediana e lunghezza whiskers   | Forma della distribuzione (asimmetrie)    |\n\n:::\n\n\n## Violin Plot\n```{=html}\n<style>\n.flex-container {\n  display: flex;\n  flex-wrap: wrap;\n  gap: 2rem;\n  margin-left: -2rem;\n  margin-right: -2rem;\n}\n\n.flex-item {\n  flex: 1 1 48%;\n  min-width: 300px;\n}\n\n.card {\n  background-color: #f9f9f9;\n  padding: 1rem;\n  border-radius: 12px;\n  box-shadow: 0 2px 6px rgba(0,0,0,0.05);\n}\n</style>\n\n<div class=\"flex-container\">\n  <div class=\"flex-item card\">\n```\n\n```{r}\nlibrary(ggplot2)\nggplot(mtcars, aes(x = factor(cyl), y = mpg)) +\n  geom_violin(fill = \"lightblue\") +\n  geom_boxplot(width = 0.1) +\n  labs(title = \"Violin Plot: MPG per Cilindri\",\n       x = \"Cilindri\", y = \"MPG\")\n```\n::: tip\n\n#### 🎻 Come si legge un violin plot? – Guida schematica e utile\n\n#### ✅ 1. **Interpreta le componenti**\n- **Forma a “violino”**: rappresenta la **distribuzione dei dati** tramite una curva di densità speculare.\n- **Larghezza** in ciascun punto verticale: indica **quanto sono frequenti i valori** in quell’intervallo.\n- **Linea interna o box centrale** (opzionale): include **mediana** e **intervallo interquartile (IQR)**, come in un boxplot.\n\n#### ✅ 2. **Valuta la densità**\n- Le **zone più larghe** rappresentano **concentrazioni di dati**.\n- Le **zone più strette** indicano valori meno frequenti.\n- A differenza del boxplot, la distribuzione non è limitata a una forma rettangolare → puoi vedere la **forma reale della distribuzione**.\n\n#### ✅ 3. **Analizza la simmetria**\n- Se le due metà del violino sono **simmetriche** → distribuzione bilanciata.\n- Se una metà è più larga o più lunga → **asimmetria**.\n\n#### ✅ 4. **Combina con il boxplot interno**\n- Se presente, il **box centrale** fornisce la **mediana** e il **range interquartile**.\n- Aiuta a confrontare **forma e centro della distribuzione** contemporaneamente.\n\n---\n\n### 📌 Riepilogo – Schema utile\n\n| Elemento               | Cosa rappresenta                        | Cosa ci dice                              |\n|------------------------|------------------------------------------|--------------------------------------------|\n| **Larghezza del violino** | Densità di dati in ogni intervallo     | Frequenza relativa                         |\n| **Forma complessiva**     | Distribuzione                         | Simmetria, multimodalità                   |\n| **Box centrale (se presente)** | Mediana + IQR                   | Tendenza centrale e variabilità            |\n| **Estremità del violino**  | Code della distribuzione              | Valori estremi (non necessariamente outlier) |\n| **Asimmetria visiva**     | Differenza tra le due metà            | Squilibri nei dati                         |\n\n:::\n\n\n## QQ plot\n```{=html}\n<style>\n.flex-container {\n  display: flex;\n  flex-wrap: wrap;\n  gap: 2rem;\n  margin-left: -2rem;\n  margin-right: -2rem;\n}\n\n.flex-item {\n  flex: 1 1 48%;\n  min-width: 300px;\n}\n\n.card {\n  background-color: #f9f9f9;\n  padding: 1rem;\n  border-radius: 12px;\n  box-shadow: 0 2px 6px rgba(0,0,0,0.05);\n}\n</style>\n\n<div class=\"flex-container\">\n  <div class=\"flex-item card\">\n```\n\n\n```{r}\nqqnorm(mtcars$mpg,\n       main = \"QQ-Plot per MPG\")\nqqline(mtcars$mpg, col = \"red\")\n```\n\n::: tip\n\n#### 📈 Come si legge un Q-Q plot? – Guida schematica e utile\n\n#### ✅ 1. **Cos’è un Q-Q plot?**\n- Un **Q-Q plot** confronta i **quantili di una variabile osservata** con i **quantili di una distribuzione teorica** (di solito **normale**).\n- Serve per **verificare se i dati seguono una certa distribuzione**.\n\n#### ✅ 2. **Leggi l’asse X e Y**\n- **Asse X**: quantili attesi (dalla distribuzione teorica).\n- **Asse Y**: quantili osservati (dai tuoi dati).\n\n---\n\n#### ✅ 3. **Interpreta l’allineamento**\n- Se i punti stanno **sulla linea diagonale** (linea di riferimento) → i dati **seguono la distribuzione teorica** (es. distribuzione normale).\n- Se i punti **deviano dalla linea** → i dati **non seguono la distribuzione attesa**.\n\n---\n\n#### ✅ 4. **Analizza le deviazioni**\n- **Deviazione in alto o in basso alle estremità** → i dati hanno **code più pesanti o leggere** rispetto alla distribuzione teorica.\n- **Curvatura a S o a gomito** → indica **asimmetria** o **skewness**:\n  - Curva **a S (convessa-concava)** → coda lunga a destra (**asimmetria positiva**).\n  - Curva **a gomito (concava-convessa)** → coda lunga a sinistra (**asimmetria negativa**).\n\n---\n\n### 📌 Riepilogo – Schema utile\n\n| Aspetto                      | Cosa osservare                          | Cosa indica                             |\n|------------------------------|------------------------------------------|------------------------------------------|\n| **Allineamento dei punti**   | Segue la linea diagonale                | I dati seguono la distribuzione teorica  |\n| **Deviazione alle estremità**| Code più o meno pesanti                 | Differenze nella coda                    |\n| **Curvatura dei punti**      | Forma a S o a gomito                    | Asimmetria (skewness)                    |\n| **Distribuzione di confronto** | Di solito normale (ma può variare)   | Deve essere nota per interpretare correttamente |\n\n:::\n\n## Scatter-plot\n```{=html}\n<style>\n.flex-container {\n  display: flex;\n  flex-wrap: wrap;\n  gap: 2rem;\n  margin-left: -2rem;\n  margin-right: -2rem;\n}\n\n.flex-item {\n  flex: 1 1 48%;\n  min-width: 300px;\n}\n\n.card {\n  background-color: #f9f9f9;\n  padding: 1rem;\n  border-radius: 12px;\n  box-shadow: 0 2px 6px rgba(0,0,0,0.05);\n}\n</style>\n\n<div class=\"flex-container\">\n  <div class=\"flex-item card\">\n```\n\n```{r}\nplot(mtcars$hp, mtcars$mpg,\n     main = \"Scatterplot: MPG vs HP\",\n     xlab = \"Cavalli (HP)\",\n     ylab = \"Consumo (MPG)\",\n     pch = 19,\n     col = \"darkgreen\")\n```\n\n\n::: tip\n\n#### 🔵 Come si legge uno scatterplot? – Guida schematica e utile\n\n#### ✅ 1. **Cosa mostra uno scatterplot?**\n- Ogni punto rappresenta **una coppia di valori** per due variabili quantitative (X e Y).\n- Serve a visualizzare **relazioni, tendenze e correlazioni** tra due variabili.\n\n---\n\n#### ✅ 2. **Leggi gli assi**\n- **Asse X (orizzontale)**: variabile indipendente (predictor).\n- **Asse Y (verticale)**: variabile dipendente (risposta).\n\n---\n\n#### ✅ 3. **Osserva la tendenza generale**\n- **Andamento crescente (↗)**: **correlazione positiva** → all’aumentare di X, aumenta anche Y.\n- **Andamento decrescente (↘)**: **correlazione negativa** → all’aumentare di X, Y diminuisce.\n- **Nessun andamento visibile**: **assenza di correlazione** → i dati sono sparsi casualmente.\n\n---\n\n#### ✅ 4. **Valuta la forza della relazione**\n- **Punti vicini a una linea ideale** → relazione forte.\n- **Punti molto dispersi** → relazione debole.\n- La forza può essere valutata visivamente o con il coefficiente di correlazione.\n\n---\n\n#### ✅ 5. **Cerca pattern o anomalie**\n- **Gruppi separati** → possibili sottogruppi (cluster).\n- **Andamenti curvi/non lineari** → possibile **relazione non lineare**.\n- **Punti lontani dalla nuvola** → **outlier** (valori anomali).\n\n---\n\n### 📌 Riepilogo – Schema utile\n\n| Aspetto                  | Cosa osservare                      | Cosa indica                              |\n|--------------------------|--------------------------------------|-------------------------------------------|\n| **Distribuzione dei punti** | Densità, forma, direzione          | Tipo di relazione (positiva, negativa, nulla) |\n| **Linearità**             | Allineamento lungo una retta        | Relazione lineare                         |\n| **Dispersione**           | Vicinanza dei punti                 | Forza della correlazione                  |\n| **Outlier**               | Punti isolati                       | Valori anomali da approfondire            |\n| **Pattern insoliti**      | Curve, gruppi, archi                | Relazioni non lineari o sottogruppi       |\n\n:::\n\n## Residual plot\n```{=html}\n<style>\n.flex-container {\n  display: flex;\n  flex-wrap: wrap;\n  gap: 2rem;\n  margin-left: -2rem;\n  margin-right: -2rem;\n}\n\n.flex-item {\n  flex: 1 1 48%;\n  min-width: 300px;\n}\n\n.card {\n  background-color: #f9f9f9;\n  padding: 1rem;\n  border-radius: 12px;\n  box-shadow: 0 2px 6px rgba(0,0,0,0.05);\n}\n</style>\n\n<div class=\"flex-container\">\n  <div class=\"flex-item card\">\n```\n\n```{r}\nmodel <- lm(mpg ~ hp, data = mtcars)\nplot(model$fitted.values, residuals(model),\n     main = \"Residual Plot\",\n     xlab = \"Fitted Values\",\n     ylab = \"Residui\",\n     pch = 19,\n     col = \"purple\")\nabline(h = 0, col = \"red\", lty = 2)\n```\n\n::: tip\n\n#### ♻️ Come si legge un residual plot? – Guida schematica e utile\n\n#### ✅ 1. **Cos’è un residual plot?**\n- Mostra i **residui** (errori) di un modello di regressione → la differenza tra i valori osservati e quelli previsti.\n- Asse X: valori **predetti** dal modello.\n- Asse Y: **residui** (valori osservati − valori predetti).\n\n---\n\n#### ✅ 2. **Obiettivo principale**\n- Verificare se i **presupposti della regressione** sono soddisfatti:\n  - Linearità\n  - Omoscedasticità (varianza costante)\n  - Assenza di pattern sistematici\n\n---\n\n#### ✅ 3. **Cosa cercare**\n\n| Pattern                         | Interpretazione                                          |\n|----------------------------------|-----------------------------------------------------------|\n| **Punti distribuiti a caso**     | ✅ Il modello è adeguato (errori casuali, omoscedastici). |\n| **Forma a U o curva**            | ❌ Mancanza di linearità → forse serve un modello non lineare. |\n| **Funnel (apertura/chiusura)**   | ❌ Eteroschedasticità → la varianza degli errori cambia. |\n| **Punti molto distanti**         | ❗ Outlier nei residui → possibili casi problematici.      |\n\n---\n\n#### ✅ 4. **Cosa idealmente si vuole vedere**\n- Una **nuvola di punti** distribuita **in modo casuale** attorno alla linea orizzontale **y = 0**.\n- Nessun pattern evidente → i residui sono indipendenti e distribuiti normalmente con media zero.\n\n---\n\n### 📌 Riepilogo – Schema utile\n\n| Aspetto                      | Cosa osservare                          | Cosa indica                               |\n|------------------------------|------------------------------------------|--------------------------------------------|\n| **Dispersione casuale**      | Punti sparsi intorno a y = 0            | Buon modello lineare                       |\n| **Pattern curvo o forma a U**| Trend sistematici nei residui           | Relazione non lineare                      |\n| **Funnel (cono aperto/chiuso)** | Varianza non costante                 | Eteroschedasticità                         |\n| **Outlier nei residui**      | Punti molto distanti                    | Osservazioni anomale o influenti           |\n:::\n\n## Boxplot per residui gruppi\n```{=html}\n<style>\n.flex-container {\n  display: flex;\n  flex-wrap: wrap;\n  gap: 2rem;\n  margin-left: -2rem;\n  margin-right: -2rem;\n}\n\n.flex-item {\n  flex: 1 1 48%;\n  min-width: 300px;\n}\n\n.card {\n  background-color: #f9f9f9;\n  padding: 1rem;\n  border-radius: 12px;\n  box-shadow: 0 2px 6px rgba(0,0,0,0.05);\n}\n</style>\n\n<div class=\"flex-container\">\n  <div class=\"flex-item card\">\n```\n\n```{r}\nboxplot(residuals(model) ~ mtcars$cyl,\n        main = \"Boxplot dei Residui per Cilindri\",\n        xlab = \"Cilindri\",\n        ylab = \"Residui\",\n        col = \"lightpink\")\n```\n\n::: tip\n\n#### 📦📊 Come si leggono i boxplot dei residui per gruppi? – Guida schematica e utile\n\n#### ✅ 1. **Cosa mostrano questi boxplot?**\n- Confrontano la **distribuzione dei residui** tra diversi **gruppi** (es. trattamenti, categorie).\n- Ogni box rappresenta **la variabilità degli errori** del modello **all’interno di un gruppo**.\n\n---\n\n#### ✅ 2. **Obiettivo principale**\n- Valutare se il modello **si comporta in modo coerente tra i gruppi**:\n  - Varianza simile? → ok\n  - Mediana dei residui ≈ 0? → ok\n  - Outlier concentrati in certi gruppi? → potenziale problema\n\n---\n\n#### ✅ 3. **Cosa osservare nei boxplot**\n\n| Osservazione                         | Interpretazione                                       |\n|--------------------------------------|--------------------------------------------------------|\n| ✅ **Box simili in tutti i gruppi**   | Residui distribuiti in modo coerente → modello stabile |\n| ✅ **Mediane vicine a 0**             | Il modello **non sovrastima né sottostima** i gruppi   |\n| ❌ **Box molto diversi tra gruppi**   | **Eteroschedasticità** → varianza non costante         |\n| ❌ **Mediane lontane da 0**           | **Sistematici errori di stima** per alcuni gruppi      |\n| ❗ **Molti outlier in un gruppo**     | Dati problematici o mal modellati                      |\n\n---\n\n#### ✅ 4. **Quando è utile usarli?**\n- Dopo aver adattato un modello lineare con **variabili categoriali**.\n- Per controllare **presupposti di omoscedasticità** (es. ANOVA, regressione con fattori).\n- Per rilevare **bias o incoerenze tra gruppi**.\n\n---\n\n### 📌 Riepilogo – Schema utile\n\n| Aspetto                     | Cosa osservare                     | Cosa indica                               |\n|-----------------------------|-------------------------------------|--------------------------------------------|\n| **Varianza dei box**        | Simile tra gruppi                  | Omogeneità delle varianze (buono)          |\n| **Mediana**                 | Vicina a 0 in ogni gruppo          | Nessun bias sistematico                    |\n| **Outlier**                 | Concentrati in pochi gruppi        | Possibili anomalie                         |\n| **Differenze forti nei box**| Modello si adatta diversamente     | Violazione presupposti del modello         |\n\n:::\n\n## Diagnostica dei modelli\n```{=html}\n<style>\n.flex-container {\n  display: flex;\n  flex-wrap: wrap;\n  gap: 2rem;\n  margin-left: -2rem;\n  margin-right: -2rem;\n}\n\n.flex-item {\n  flex: 1 1 48%;\n  min-width: 300px;\n}\n\n.card {\n  background-color: #f9f9f9;\n  padding: 1rem;\n  border-radius: 12px;\n  box-shadow: 0 2px 6px rgba(0,0,0,0.05);\n}\n</style>\n\n<div class=\"flex-container\">\n  <div class=\"flex-item card\">\n```\n\n```{r, fig.width=12, fig.height=10}\nlibrary(performance)\nlibrary(see)\n\nmodel <- lm(mpg ~ hp + wt, data = mtcars)\n\ncheck_model(model)\n```\n::: tip\n\n#### 🧾 Interpretazione dei grafici diagnostici – `check_model()`\n\n#### ✅ 1. **Residuals vs Fitted**\n- **Distribuzione casuale** attorno alla linea orizzontale indica:\n  - Corretta specificazione del modello\n  - Varianza costante (omoschedasticità)\n- **Pattern (curve, funnel)** → possibile violazione di linearità o eteroschedasticità.\n\n---\n\n#### ✅ 2. **Q-Q Plot dei residui**\n- **Punti allineati alla diagonale** → i residui seguono una distribuzione normale.\n- **Deviazioni marcate alle estremità** → possibili problemi di normalità (code pesanti o leggere).\n\n---\n\n#### ✅ 3. **Scale-Location (Spread vs Fitted)**\n- Verifica la **costanza della varianza dei residui**.\n- **Dispersione uniforme** → ok.\n- **Funnel o variazioni di ampiezza** → eteroschedasticità.\n\n---\n\n#### ✅ 4. **Residuals vs Leverage**\n- Identifica **osservazioni influenti**.\n- Punti con **alto leverage e residui grandi** → potrebbero avere **impatto eccessivo** sul modello.\n- Da esaminare singolarmente (possibili outlier o errori).\n\n:::\n\n## Predicted vs Actual\n```{=html}\n<style>\n.flex-container {\n  display: flex;\n  flex-wrap: wrap;\n  gap: 2rem;\n  margin-left: -2rem;\n  margin-right: -2rem;\n}\n\n.flex-item {\n  flex: 1 1 48%;\n  min-width: 300px;\n}\n\n.card {\n  background-color: #f9f9f9;\n  padding: 1rem;\n  border-radius: 12px;\n  box-shadow: 0 2px 6px rgba(0,0,0,0.05);\n}\n</style>\n\n<div class=\"flex-container\">\n  <div class=\"flex-item card\">\n```\n\n```{r}\nplot(mtcars$mpg, model$fitted.values,\n     main = \"Predicted vs Actual\",\n     xlab = \"Valori Osservati (MPG)\",\n     ylab = \"Valori Predetti\",\n     pch = 19,\n     col = \"blue\")\nabline(a = 0, b = 1, col = \"red\", lty = 2)\n```\n\n::: tip\n\n#### 🔮 Interpretazione del grafico Predicted vs Actual\n\n#### ✅ 1. **Cosa mostra questo grafico?**\n- Confronta i **valori previsti dal modello** (asse X) con i **valori osservati reali** (asse Y).\n- Utile per valutare **l’accuratezza del modello**: quanto bene le previsioni replicano i dati osservati?\n\n---\n\n#### ✅ 2. **Interpretazione ideale**\n- I punti **dovrebbero allinearsi lungo la diagonale** (linea y = x).\n- Una buona aderenza alla diagonale indica:\n  - Previsioni accurate\n  - Buona capacità del modello di rappresentare i dati reali\n\n---\n\n#### ✅ 3. **Segnali da osservare**\n\n| Comportamento dei punti          | Cosa indica                              |\n|----------------------------------|-------------------------------------------|\n| ✅ Allineamento lungo la diagonale | Previsioni vicine ai valori reali (ottimo) |\n| ❌ Deviazione sistematica         | Bias del modello (sottostima o sovrastima) |\n| ❌ Dispersione elevata            | Previsioni poco precise                   |\n| ❌ Pattern curvi o gruppi         | Modello mal specificato o relazioni non lineari |\n\n---\n\n#### ✅ 4. **Quando usarlo?**\n- In ogni modello di regressione o predizione (lineare, logistico, machine learning).\n- Per valutare la **qualità globale delle previsioni**.\n\n:::\n\n## Curva di potenza\n\n```{=html}\n<style>\n.flex-container {\n  display: flex;\n  flex-wrap: wrap;\n  gap: 2rem;\n  margin-left: -2rem;\n  margin-right: -2rem;\n}\n\n.flex-item {\n  flex: 1 1 48%;\n  min-width: 300px;\n}\n\n.card {\n  background-color: #f9f9f9;\n  padding: 1rem;\n  border-radius: 12px;\n  box-shadow: 0 2px 6px rgba(0,0,0,0.05);\n}\n</style>\n\n<div class=\"flex-container\">\n  <div class=\"flex-item card\">\n```\n\n\n```{r}\n\n\nlibrary(ggplot2)\n\n# Parametri fissi\nn1 <- 30\nn2 <- 30\nalpha <- 0.05\ndf <- n1 + n2 - 2\ncohens_d <- seq(0, 1.5, length.out = 300)\n\n# Funzione per calcolare la potenza\ncalc_power <- function(d) {\n  ncp <- d * sqrt(n1 * n2 / (n1 + n2))  # parametro non centrale\n  crit <- qt(1 - alpha, df)             # soglia critica (test unilaterale)\n  1 - pt(crit, df, ncp)                 # potenza = 1 - P non rilevata\n}\n\n# Applica la funzione a tutta la sequenza di d\npower_vals <- sapply(cohens_d, calc_power)\n\n# Crea un data frame\ndf_power <- data.frame(\n  d = cohens_d,\n  power = power_vals\n)\n\n# Plot con ggplot2\nggplot(df_power, aes(x = d, y = power)) +\n  geom_line(color = \"blue\", size = 1) +\n  geom_hline(yintercept = 0.8, linetype = \"dotted\", color = \"darkgreen\") +\n  geom_vline(xintercept = 0.5, linetype = \"dashed\", color = \"red\") +\n  labs(\n    title = \"Curva di potenza tipica (t-test a due campioni, unilaterale)\",\n    x = \"Cohen's d (dimensione dell'effetto)\",\n    y = \"Potenza (1 - β)\"\n  ) +\n  theme_minimal()\n```\n\n::: tip\n\n#### ⚡ Interpretazione della Curva di Potenza (Power Curve)\n\n#### ✅ 1. **Cos’è la curva di potenza?**\n- Mostra come **la probabilità di rilevare un effetto reale** (potenza statistica) varia al cambiare della dimensione dell’effetto o del numero di osservazioni.\n- Asse X: **Dimensione dell’effetto** o **dimensione del campione (n)**\n- Asse Y: **Potenza statistica** (P = 1 - β), cioè la probabilità di **rifiutare correttamente H₀**.\n\n---\n\n#### ✅ 2. **Interpretazione dei valori**\n- Una potenza ≥ **0.80** (80%) è **considerata adeguata** → bassa probabilità di errore di tipo II.\n- Valori più bassi indicano **scarsa sensibilità del test** → alto rischio di non rilevare un effetto reale.\n- La curva mostra **quanta potenza si guadagna** aumentando il campione o l’effetto.\n\n---\n\n#### ✅ 3. **Cosa osservare nella curva**\n\n| Forma della curva                 | Interpretazione                                      |\n|----------------------------------|------------------------------------------------------|\n| 📈 Curva crescente e appiattita  | All’aumentare di n, la potenza si stabilizza        |\n| 🎯 Punto in cui P ≈ 0.80         | Soglia ottimale per scegliere la dimensione campione |\n| ❗ Curva piatta a valori bassi   | Effetto troppo piccolo per essere rilevabile         |\n\n---\n\n#### ✅ 4. **Quando usarla?**\n- In fase di **pianificazione dello studio** → per determinare **quanti soggetti servono**.\n- Per verificare se un test ha **potenza sufficiente** a rilevare un effetto atteso.\n\n---\n\n### 📌 Obiettivo finale\n- **Assicurarsi che il test abbia un’alta probabilità di successo**, evitando sprechi di risorse o conclusioni false negative.\n\n:::"},"formats":{"html":{"identifier":{"display-name":"HTML","target-format":"html","base-format":"html"},"execute":{"fig-width":7,"fig-height":5,"fig-format":"retina","fig-dpi":96,"df-print":"default","error":false,"eval":true,"cache":null,"freeze":false,"echo":false,"output":true,"warning":false,"include":true,"keep-md":false,"keep-ipynb":false,"ipynb":null,"enabled":null,"daemon":null,"daemon-restart":false,"debug":false,"ipynb-filters":[],"ipynb-shell-interactivity":null,"plotly-connected":true,"message":false,"engine":"knitr"},"render":{"keep-tex":false,"keep-typ":false,"keep-source":false,"keep-hidden":false,"prefer-html":false,"output-divs":true,"output-ext":"html","fig-align":"default","fig-pos":null,"fig-env":null,"code-fold":false,"code-overflow":"scroll","code-link":false,"code-line-numbers":false,"code-tools":false,"tbl-colwidths":"auto","merge-includes":true,"inline-includes":false,"preserve-yaml":false,"latex-auto-mk":true,"latex-auto-install":true,"latex-clean":true,"latex-min-runs":1,"latex-max-runs":10,"latex-makeindex":"makeindex","latex-makeindex-opts":[],"latex-tlmgr-opts":[],"latex-input-paths":[],"latex-output-dir":null,"link-external-icon":false,"link-external-newwindow":false,"self-contained-math":false,"format-resources":[],"notebook-links":true},"pandoc":{"standalone":true,"wrap":"none","default-image-extension":"png","to":"html","include-in-header":["assets/header.html"],"self-contained":true,"toc":true,"toc-depth":3,"css":["assets/custom.css"],"output-file":"Grafici.html"},"language":{"toc-title-document":"Table of contents","toc-title-website":"On this page","related-formats-title":"Other Formats","related-notebooks-title":"Notebooks","source-notebooks-prefix":"Source","other-links-title":"Other Links","code-links-title":"Code Links","launch-dev-container-title":"Launch Dev Container","launch-binder-title":"Launch Binder","article-notebook-label":"Article Notebook","notebook-preview-download":"Download Notebook","notebook-preview-download-src":"Download Source","notebook-preview-back":"Back to Article","manuscript-meca-bundle":"MECA Bundle","section-title-abstract":"Abstract","section-title-appendices":"Appendices","section-title-footnotes":"Footnotes","section-title-references":"References","section-title-reuse":"Reuse","section-title-copyright":"Copyright","section-title-citation":"Citation","appendix-attribution-cite-as":"For attribution, please cite this work as:","appendix-attribution-bibtex":"BibTeX citation:","appendix-view-license":"View License","title-block-author-single":"Author","title-block-author-plural":"Authors","title-block-affiliation-single":"Affiliation","title-block-affiliation-plural":"Affiliations","title-block-published":"Published","title-block-modified":"Modified","title-block-keywords":"Keywords","callout-tip-title":"Tip","callout-note-title":"Note","callout-warning-title":"Warning","callout-important-title":"Important","callout-caution-title":"Caution","code-summary":"Code","code-tools-menu-caption":"Code","code-tools-show-all-code":"Show All Code","code-tools-hide-all-code":"Hide All Code","code-tools-view-source":"View Source","code-tools-source-code":"Source Code","tools-share":"Share","tools-download":"Download","code-line":"Line","code-lines":"Lines","copy-button-tooltip":"Copy to Clipboard","copy-button-tooltip-success":"Copied!","repo-action-links-edit":"Edit this page","repo-action-links-source":"View source","repo-action-links-issue":"Report an issue","back-to-top":"Back to top","search-no-results-text":"No results","search-matching-documents-text":"matching documents","search-copy-link-title":"Copy link to search","search-hide-matches-text":"Hide additional matches","search-more-match-text":"more match in this document","search-more-matches-text":"more matches in this document","search-clear-button-title":"Clear","search-text-placeholder":"","search-detached-cancel-button-title":"Cancel","search-submit-button-title":"Submit","search-label":"Search","toggle-section":"Toggle section","toggle-sidebar":"Toggle sidebar navigation","toggle-dark-mode":"Toggle dark mode","toggle-reader-mode":"Toggle reader mode","toggle-navigation":"Toggle navigation","crossref-fig-title":"Figure","crossref-tbl-title":"Table","crossref-lst-title":"Listing","crossref-thm-title":"Theorem","crossref-lem-title":"Lemma","crossref-cor-title":"Corollary","crossref-prp-title":"Proposition","crossref-cnj-title":"Conjecture","crossref-def-title":"Definition","crossref-exm-title":"Example","crossref-exr-title":"Exercise","crossref-ch-prefix":"Chapter","crossref-apx-prefix":"Appendix","crossref-sec-prefix":"Section","crossref-eq-prefix":"Equation","crossref-lof-title":"List of Figures","crossref-lot-title":"List of Tables","crossref-lol-title":"List of Listings","environment-proof-title":"Proof","environment-remark-title":"Remark","environment-solution-title":"Solution","listing-page-order-by":"Order By","listing-page-order-by-default":"Default","listing-page-order-by-date-asc":"Oldest","listing-page-order-by-date-desc":"Newest","listing-page-order-by-number-desc":"High to Low","listing-page-order-by-number-asc":"Low to High","listing-page-field-date":"Date","listing-page-field-title":"Title","listing-page-field-description":"Description","listing-page-field-author":"Author","listing-page-field-filename":"File Name","listing-page-field-filemodified":"Modified","listing-page-field-subtitle":"Subtitle","listing-page-field-readingtime":"Reading Time","listing-page-field-wordcount":"Word Count","listing-page-field-categories":"Categories","listing-page-minutes-compact":"{0} min","listing-page-category-all":"All","listing-page-no-matches":"No matching items","listing-page-words":"{0} words","listing-page-filter":"Filter","draft":"Draft"},"metadata":{"lang":"en","fig-responsive":true,"quarto-version":"1.6.42","title":"Grafici","subtitle":"","author":"","editor":"visual","toc-expand":3,"message":false,"theme":"cosmo"},"extensions":{"book":{"multiFile":true}}}},"projectFormats":["html"]}